hrl_pybullet_envs/__init__.py
hrl_pybullet_envs/utils.py
hrl_pybullet_envs/assets/__init__.py
hrl_pybullet_envs/assets/ant.xml
hrl_pybullet_envs/assets/box.xml
hrl_pybullet_envs/assets/food.xml
hrl_pybullet_envs/assets/plane.xml
hrl_pybullet_envs/assets/player_cube.xml
hrl_pybullet_envs/assets/poison.xml
hrl_pybullet_envs/assets/wall.xml
hrl_pybullet_envs/envs/MjAnt.py
hrl_pybullet_envs/envs/__init__.py
hrl_pybullet_envs/envs/intersection_utils.py
hrl_pybullet_envs/envs/sizeable_enclosed_scene.py
hrl_pybullet_envs/envs/ant_flagrun/__init__.py
hrl_pybullet_envs/envs/ant_flagrun/ant_flagrun_env.py
hrl_pybullet_envs/envs/ant_maze/__init__.py
hrl_pybullet_envs/envs/ant_maze/ant_maze_bullet_env.py
hrl_pybullet_envs/envs/ant_maze/ant_maze_mj_env.py
hrl_pybullet_envs/envs/ant_maze/maze_scene.py
hrl_pybullet_envs/envs/gather/__init__.py
hrl_pybullet_envs/envs/gather/ant_gather_env.py
hrl_pybullet_envs/envs/gather/gather_base.py
hrl_pybullet_envs/envs/gather/gather_scene.py
hrl_pybullet_envs/envs/gather/point_bot.py
hrl_pybullet_envs/envs/gather/point_gather_env.py
hrl_pybullet_envs-0.2.37.dist-info/LICENSE
hrl_pybullet_envs-0.2.37.dist-info/METADATA
hrl_pybullet_envs-0.2.37.dist-info/WHEEL
hrl_pybullet_envs-0.2.37.dist-info/top_level.txt
hrl_pybullet_envs-0.2.37.dist-info/RECORD
