Metadata-Version: 2.1
Name: hrl_pybullet_envs
Version: 0.2.37
Summary: Locomotion HRL envs in pybullet
Home-page: https://github.com/sash-a/hrl_pybullet_envs
Author: Sasha Abramowitz
Author-email: reallysasha@gmail.com
License: UNKNOWN
Platform: UNKNOWN
Classifier: Programming Language :: Python :: 3
Classifier: License :: OSI Approved :: GNU General Public License v3 or later (GPLv3+)
Classifier: Operating System :: OS Independent
Requires-Python: >=3.6
License-File: LICENSE
